chaotic/__init__.py
chaotic/app.py
chaotic/log.py
chaotic/version.py
chaotic/cloud/__init__.py
chaotic/cloud/cloudscale_ch.py
chaotic/cloud/cloudstack.py
chaotic/cloud/digitalocean.py
chaotic/cloud/exoscale.py
chaotic/cloud/hcloud.py
chaotic/cloud/nomad.py
chaotic/cloud/nomad_node.py
chaotic/cloud/proxmox_kvm.py
chaotic/cloud/vultr.py
chaotic_ngine_kunal-0.8.1.dist-info/LICENSE
chaotic_ngine_kunal-0.8.1.dist-info/METADATA
chaotic_ngine_kunal-0.8.1.dist-info/WHEEL
chaotic_ngine_kunal-0.8.1.dist-info/entry_points.txt
chaotic_ngine_kunal-0.8.1.dist-info/top_level.txt
chaotic_ngine_kunal-0.8.1.dist-info/RECORD
