Metadata-Version: 2.1
Name: chaotic-ngine-kunal
Version: 0.8.1
Summary: Chaos for Clouds.
Home-page: https://github.com/ngine-io/chaotic
Author: René Moser
Author-email: mail@renemoser.net
License: MIT
Classifier: Intended Audience :: Developers
Classifier: Intended Audience :: System Administrators
Classifier: Development Status :: 4 - Beta
Classifier: Programming Language :: Python :: 3
Classifier: License :: OSI Approved :: MIT License
Classifier: Operating System :: OS Independent
Classifier: Environment :: Web Environment
Requires-Python: >=3.6
License-File: LICENSE
Requires-Dist: cloudscale-sdk (==0.7.0)
Requires-Dist: cs (==3.0.0)
Requires-Dist: hcloud (==1.18.2)
Requires-Dist: proxmoxer (==1.3.1)
Requires-Dist: python-digitalocean (==1.17.0)
Requires-Dist: python-dotenv (==0.21.0)
Requires-Dist: python-json-logger (==2.0.4)
Requires-Dist: pyyaml (==6.0)
Requires-Dist: requests (==2.28.2)
Requires-Dist: schedule (==1.1.0)
